README.rst
flask_tasktiger.py
setup.cfg
setup.py
Flask_TaskTiger.egg-info/PKG-INFO
Flask_TaskTiger.egg-info/SOURCES.txt
Flask_TaskTiger.egg-info/dependency_links.txt
Flask_TaskTiger.egg-info/requires.txt
Flask_TaskTiger.egg-info/top_level.txt