Metadata-Version: 1.1
Name: Flask-TaskTiger
Version: 0.0.1
Summary: Flask TaskTiger
Home-page: UNKNOWN
Author: Charlie Wolf
Author-email: charlie@flow180.com
License: Tequilaware
Platform: UNKNOWN
Classifier: Programming Language :: Python :: 3
Classifier: Programming Language :: Python :: 2
Classifier: Topic :: Utilities
